playsound3/__init__.py
playsound3/backends.py
playsound3/playsound3.py
playsound3/py.typed
playsound3-3.2.7.dist-info/METADATA
playsound3-3.2.7.dist-info/WHEEL
playsound3-3.2.7.dist-info/licenses/LICENSE
playsound3-3.2.7.dist-info/RECORD
