Metadata-Version: 2.4
Name: playsound3
Version: 3.2.7
Summary: Cross-platform library to play audio files
Project-URL: Home, https://github.com/sjmikler/playsound3
Project-URL: Issues, https://github.com/sjmikler/playsound3/issues
Project-URL: Documentation, https://github.com/sjmikler/playsound3/blob/main/README.md#quick-start
Author-email: Szymon Mikler <sjmikler@gmail.com>, Taylor Marks <taylor@marksfam.com>
Maintainer-email: Szymon Mikler <sjmikler@gmail.com>
License: MIT License
License-File: LICENSE
Keywords: audio,media,mp3,music,play,playsound,song,sound,wav,wave
Classifier: Development Status :: 4 - Beta
Classifier: Intended Audience :: Developers
Classifier: License :: OSI Approved :: MIT License
Classifier: Operating System :: OS Independent
Classifier: Programming Language :: Python :: 3
Classifier: Programming Language :: Python :: 3.7
Classifier: Programming Language :: Python :: 3.8
Classifier: Programming Language :: Python :: 3.9
Classifier: Programming Language :: Python :: 3.10
Classifier: Programming Language :: Python :: 3.11
Classifier: Programming Language :: Python :: 3.12
Classifier: Programming Language :: Python :: 3.13
Classifier: Topic :: Multimedia :: Sound/Audio :: MIDI
Classifier: Topic :: Multimedia :: Sound/Audio :: Players
Classifier: Topic :: Multimedia :: Sound/Audio :: Players :: MP3
Classifier: Typing :: Typed
Requires-Python: >=3.7
Requires-Dist: pywin32; sys_platform == 'win32'
Requires-Dist: typing-extensions; python_version < '3.8'
Provides-Extra: dev
Requires-Dist: pyright; extra == 'dev'
Requires-Dist: pytest; extra == 'dev'
Requires-Dist: ruff; extra == 'dev'
